README.rst
setup.cfg
setup.py
sg_helper/__init__.py
sg_helper/sg_helper.py
sg_helper.egg-info/PKG-INFO
sg_helper.egg-info/SOURCES.txt
sg_helper.egg-info/dependency_links.txt
sg_helper.egg-info/requires.txt
sg_helper.egg-info/top_level.txt