Metadata-Version: 1.1
Name: sg-helper
Version: 0.0.0
Summary: A numpy interface for the SG++ adaptive sparse grids library
Home-page: https://github.com/dgreenwald/sg_helper
Author: Dan Greenwald
Author-email: greenw2@gmail.com
License: MIT
Keywords: adaptive sparse grids
Platform: UNKNOWN
Classifier: Development Status :: 3 - Alpha
Classifier: License :: OSI Approved :: MIT License
Classifier: Programming Language :: Python :: 2
Classifier: Programming Language :: Python :: 2.6
Classifier: Programming Language :: Python :: 2.7
